gemini_live_ws_server_OMANANDSWAMI/src/__init__.py
gemini_live_ws_server_OMANANDSWAMI/src/main_server.py
gemini_live_ws_server-0.1.2.dist-info/METADATA
gemini_live_ws_server-0.1.2.dist-info/WHEEL
gemini_live_ws_server-0.1.2.dist-info/top_level.txt
gemini_live_ws_server-0.1.2.dist-info/RECORD
